[{
    "name": "Impulse City",
    "file": "impulse-city"
},{
    "name": "Ancient Warriors",
    "file": "ancient-warriors"
},{
    "name": "Agumon EX",
    "file": "agumon-ex"
},{
    "name": "Gabumon EX",
    "file": "gabumon-ex"
},{
    "name": "Volcanic Beat",
    "file": "volcanic-beat"
},{
    "name": "Blizzard Fang",
    "file": "blizzard-fang"
},{
    "name": "Infinite Tide",
    "file": "infinite-tide"
},{
    "name": "Titan of Dust",
    "file": "titan-of-dust"
},{
    "name": "Hermit in the Jungle",
    "file": "hermit-in-the-jungle"
},{
    "name": "Nu Metal Empire",
    "file": "nu-metal-empire"
},{
    "name": "Dynasty of the Evil",
    "file": "dynasty-of-the-evil"
},{
    "name": "Mad Black Roar",
    "file": "mad-black-roar"
},{
    "name": "True Shadow Howl",
    "file": "true-shadow-howl"
},{
    "name": "Gammamon",
    "file": "gammamon"
},{
    "name": "Angoramon",
    "file": "angoramon"
},{
    "name": "Jellymon",
    "file": "jellymon"
},{
    "name": "Guilmon EX",
    "file": "guilmon-ex"
},{
    "name": "Terriermon EX",
    "file": "terriermon-ex"
},{
    "name": "Renamon EX",
    "file": "renamon-ex"
},{
    "name": "Primeval Warriors",
    "file": "primeval-warriors"
},{
    "name": "Espimon",
    "file": "espimon"
},{
    "name": "Ryudamon",
    "file": "ryudamon"
},{
    "name": "Agnimon EX",
    "file": "agnimon-ex"
},{
    "name": "Fairimon EX",
    "file": "fairimon-ex"
},{
    "name": "Chackmon EX",
    "file": "chackmon-ex"
},{
    "name": "Wolfmon EX",
    "file": "wolfmon-ex"
},{
    "name": "Blitzmon EX",
    "file": "blitzmon-ex"
},{
    "name": "Louwemon EX",
    "file": "louwemon-ex"
},{
    "name": "Dinosaur Roar",
    "file": "dinosaur-roar"
},{
    "name": "Wolf Howl",
    "file": "wolf-howl"
},{
    "name": "Medarot",
    "file": "medarot"
},{
    "name": "Black Roar",
    "file": "black-roar"
},{
    "name": "Shadow Howl",
    "file": "shadow-howl"
},{
    "name": "Guilmon GP",
    "file": "guilmon-gp"
},{
    "name": "Impmon GP",
    "file": "impmon-gp"
},{
    "name": "Renamon GP",
    "file": "renamon-gp"
},{
    "name": "Monodramon GP",
    "file": "monodramon-gp"
}]